aws_lambda_mess/__about__.py
aws_lambda_mess/cli.py
aws_lambda_mess/framework/Route.py
aws_lambda_mess/framework/failures.py
aws_lambda_mess/framework/lambda_dispatcher.py
aws_lambda_mess/framework/server.py
aws_lambda_mess/framework/success.py
aws_lambda_mess/init_files/.aws_lambda_mess.json
aws_lambda_mess/init_files/.gitignore
aws_lambda_mess/init_files/app.py
aws_lambda_mess/init_files/requirements.txt
aws_lambda_mess-0.0.9.dist-info/METADATA
aws_lambda_mess-0.0.9.dist-info/WHEEL
aws_lambda_mess-0.0.9.dist-info/entry_points.txt
aws_lambda_mess-0.0.9.dist-info/RECORD
